{
  "version": 1,
  "exportedAt": 1773111538070,
  "entries": [
    {
      "id": "e1772653553918-w2g92u",
      "source": "Curriculum Vitae",
      "translation": "Жизненный путь",
      "transcription": "[kʊˈrɪkʊlʊm ˈviːtaɪ]",
      "fromLang": "la",
      "toLang": "ru",
      "addedAt": 1772653553918
    },
    {
      "id": "e1772632036893-002fhd",
      "source": "weak",
      "translation": "слабый",
      "transcription": "/wiːk/",
      "fromLang": "en",
      "toLang": "ru",
      "addedAt": 1772632036893
    },
    {
      "id": "e1772569140463-xubnzc",
      "source": "Zahtev",
      "translation": "Запрос",
      "transcription": "[zɑːtˈlɛf]",
      "fromLang": "sr",
      "toLang": "ru",
      "addedAt": 1772569140463
    },
    {
      "id": "e1772568132688-hktock",
      "source": "Могу ли оплатить алкоголь на кассе самообсуживания",
      "translation": "Можете ли платити алкохол на каси самоуслуживања",
      "transcription": "[ˈmoɡʊ lʲɪ ɐplɐˈtʲitʲ ɐɫkɐˈɡolʲ nɐ‿ˈkaɕːɪ səməʊsˈlʉʐɨvənʲɪɪ̯ə]",
      "fromLang": "ru",
      "toLang": "sr",
      "addedAt": 1772568132688
    },
    {
      "id": "e1772554848729-fvn4jk",
      "source": "Zatvoreno",
      "translation": "Закрыто",
      "transcription": "/zætˈvɔːɹənoʊ/",
      "fromLang": "sr",
      "toLang": "ru",
      "addedAt": 1772554848729
    },
    {
      "id": "e1772526821922-3rd56z",
      "source": "Nevreme",
      "translation": "Поздно",
      "transcription": "/nɛvˈɹiːm/",
      "fromLang": "en",
      "toLang": "ru",
      "addedAt": 1772526821922
    }
  ],
  "priorityLangs": [
    "en",
    "sr",
    "de",
    "es",
    "pt",
    "it",
    "fr",
    "la"
  ]
}