{
  "version": 1,
  "exportedAt": 1772669838616,
  "notes": [
    {
      "id": "2026-03-05_03-17-15",
      "title": "",
      "content": "",
      "folderId": null,
      "createdAt": 1772669835657,
      "updatedAt": 1772669835657,
      "tags": [],
      "color": "none",
      "todos": []
    },
    {
      "id": "2026-03-05_02-33-50",
      "title": "Todo Civil 3d",
      "content": "<h2>Ответ Gemini</h2><p>Как итог нашего обсуждения, ниже представлена концепция <strong>Smart Site Design Engine</strong> — кастомного параметрического движка для AutoCAD/Civil 3D на базе C#.</p><hr><h2><strong>1. Цели и философия системы</strong></h2><ul><li><p><strong>Уход от рутины:</strong> Превращение черчения «линия за линией» в управление системой связей.</p></li><li><p><strong>Безотказность правки:</strong> При перемещении здания или дороги весь прилегающий генплан (отмостки, борта, лотки, штриховки) перестраивается мгновенно.</p></li><li><p><strong>Целостность данных:</strong> Штриховки и ведомости (ТЭП) всегда на 100% соответствуют фактической геометрии.</p></li></ul><hr><h2><strong>2. Основная логика и Механизмы (Backend)</strong></h2><ul><li><p><strong>XData / Extension Dictionary:</strong> Каждому объекту присваивается «паспорт» (ID родителя, тип связи, параметры — радиус, отступ).</p></li><li><p><strong>Граф зависимостей:</strong> Система хранит дерево связей. <em>Здание (Корень) → Отмостка → Борт → Лоток → Сопряжение (Дуга).</em></p></li><li><p><strong>Событийная модель (Event Listeners):</strong></p><ul><li><p><code>ObjectModified</code>: запускает каскадное обновление зависимых объектов.</p></li><li><p><code>ObjectErased</code>: активирует протоколы безопасности (удаление дочерних или подсвечивание «осиротевших» объектов).</p></li><li><p><code>CommandEnded</code>: точка финального пересчета геометрии (чтобы не тормозить процесс перемещения).</p></li></ul></li></ul><hr><h2><strong>3. Ключевые функции и Методы</strong></h2><ul><li><p><strong>Smart Fillet (Умное сопряжение):</strong> Метод вычисляет касательные точки (TTR) между двумя линиями. При сдвиге любой линии дуга пересчитывается, а линии автоматически укорачиваются или удлиняются (<code>Extend</code>/<code>Trim</code>).</p></li><li><p><strong>Constraint Offset (Параллельность):</strong> Удержание линии на фиксированном расстоянии от родителя. Поддерживает «просечки» (разрывы в местах пересечения с другими объектами).</p></li><li><p><strong>Virtual Boundary (Синтез контура):</strong> Для генерации штриховок код создает временный невидимый <code>CurveLoop</code>. Если реальные линии не доведены, алгоритм «замыкает» их математически.</p></li><li><p><strong>Hatch Background Engine:</strong> Вынос генерации штриховок во внешний файл через XRef для сохранения быстродействия основного чертежа.</p></li></ul><hr><h2><strong>4. Пользовательский интерфейс (UI/UX)</strong></h2><ul><li><p><strong>Smart Properties Palette (Панель свойств):</strong></p><ul><li><p>Отображение иерархии: кто родитель, кто дочерний.</p></li><li><p>Изменение параметров «на лету» (изменить радиус всех сопряжений квартала одним вводом).</p></li><li><p>Статус связи: «ОК» или «Ошибка».</p></li></ul></li><li><p><strong>Индикация и Глифы (Overrule):</strong></p><ul><li><p>Визуальные иконки «замочков» или «цепей» над объектами.</p></li><li><p><strong>Знак вопроса (?)</strong>: Подсветка объектов, связь которых разорвана или геометрия которых стала математически невозможной.</p></li></ul></li><li><p><strong>Service Layer (Служебный слой):</strong> Непечатаемая графика, отрисовывающая векторы связей (пунктиры от объекта к объекту).</p></li></ul><hr><h2><strong>5. Примеры практического применения</strong></h2><ul><li><p><strong>Отмостка:</strong> Двигаем контур здания — отмостка следует за ним, автоматически прерываясь в местах крылец или подрезаясь по линии борта.</p></li><li><p><strong>Перекресток:</strong> Сдвигаем ось дороги — борта, лотки и дуги закругления перестраиваются, сохраняя нормативные радиусы.</p></li><li><p><strong>Парковка:</strong> Изменяем длину линии кармана — количество машиномест и разметка пересчитываются автоматически.</p></li><li><p><strong>Лоток:</strong> Генерация линии лотка вдоль борта с автоматической «срезкой» на пересечении с въездами.</p></li></ul><hr><h2><strong>6. Метод реализации (Stack)</strong></h2><ul><li><p><strong>Язык:</strong> C# (.NET API AutoCAD).</p></li><li><p><strong>Геометрия:</strong> <code>Autodesk.AutoCAD.Geometry</code> (векторный анализ).</p></li><li><p><strong>Внешние библиотеки:</strong> <em>Clipper</em> (для сложных операций с контурами штриховок).</p></li><li><p><strong>Диагностика:</strong> Команда <code>CHECK_LINKS</code>, которая сканирует чертеж и предлагает «Попытку автоматического восстановления» (Re-solve) для всех проблемных зон.</p></li></ul><p></p>",
      "folderId": null,
      "createdAt": 1772667230510,
      "updatedAt": 1772667249969,
      "tags": [],
      "color": "red"
    },
    {
      "id": "2026-03-03_20-39-56",
      "title": "Экспорт",
      "content": "<p>1</p>",
      "folderId": null,
      "createdAt": 1772566796993,
      "updatedAt": 1772566807402,
      "tags": [],
      "color": "none",
      "archived": false,
      "todos": []
    }
  ],
  "folders": []
}