{
  "version": 1,
  "exportedAt": 1773398789517,
  "tasks": [
    {
      "id": "task-1772571999893",
      "name": "Среда_КУ_ТЧ+Оcтальные_листы",
      "start": 1773608400000,
      "end": 1773783600000,
      "progress": 0,
      "type": "task",
      "labels": [
        "Миша"
      ]
    },
    {
      "id": "task-1772575951902",
      "name": "ПОР_Строгино_нежилая_часть",
      "start": 1773372000000,
      "end": 1773783600000,
      "progress": 0,
      "type": "task",
      "labels": [
        "Игорь"
      ]
    },
    {
      "id": "task-1772575977852",
      "name": "ЛЛМ_КГП_3-4-5",
      "start": 1773778800000,
      "end": 1773951600000,
      "progress": 0,
      "type": "task",
      "labels": [
        "Игорь"
      ]
    },
    {
      "id": "task-1772617544674",
      "name": "360_к1.3: КДО, ОДИ",
      "start": 1773789600000,
      "end": 1773951600000,
      "progress": 0,
      "type": "task",
      "labels": [
        "Катя"
      ]
    },
    {
      "id": "task-1772620395634",
      "name": "360_к2_ПД",
      "start": 1773780000000,
      "end": 1774989600000,
      "progress": 0,
      "type": "task",
      "labels": [
        "Миша"
      ]
    },
    {
      "id": "task-1772647907091",
      "name": "Обсудить с Катей - что делать по ЗнП и т.п.",
      "start": 1773619200000,
      "end": 1773692400000,
      "progress": 0,
      "type": "task",
      "labels": [
        "Катя"
      ]
    },
    {
      "id": "task-1772650530165",
      "name": "Посчитать ТЭП в воронку",
      "start": 1773384000000,
      "end": 1773434400000,
      "progress": 0,
      "type": "task",
      "labels": [
        "Миша"
      ]
    },
    {
      "id": "task-1773230917213",
      "name": "ХП8_запись и замечания",
      "start": 1773351600000,
      "end": 1773392400000,
      "progress": 0,
      "type": "task",
      "labels": [
        "Миша"
      ]
    },
    {
      "id": "task-1773231186524",
      "name": "ЛЛМЗ_12_РнВ",
      "start": 1773354000000,
      "end": 1773390000000,
      "progress": 0,
      "type": "task",
      "labels": [
        "Миша"
      ]
    },
    {
      "id": "task-1773257127315",
      "name": "360_к1.3: АГР, в т.ч. обводки",
      "start": 1773619200000,
      "end": 1773775200000,
      "progress": 0,
      "type": "task",
      "labels": [
        "Катя"
      ]
    },
    {
      "id": "task-1773363196682",
      "name": "Среда_к3 - учесть мою таблицу в части к.1.1",
      "start": 1773616800000,
      "end": 1773774000000,
      "progress": 0,
      "type": "task",
      "labels": [
        "Миша"
      ]
    },
    {
      "id": "task-1773391678287",
      "name": "360_к2_Выдать КДО",
      "start": 1773878400000,
      "end": 1775088000000,
      "progress": 0,
      "type": "task",
      "labels": [
        "Миша"
      ]
    },
    {
      "id": "task-1773396582218",
      "name": "ЛЛМ_КГП_3-4-5_ПОР",
      "start": 1773955200000,
      "end": 1775649600000,
      "progress": 0,
      "type": "task",
      "labels": [
        "Игорь"
      ]
    },
    {
      "id": "task-1773398786992",
      "name": "Новая задача",
      "start": 1775649600000,
      "end": 1775822400000,
      "progress": 0,
      "type": "task"
    }
  ],
  "labels": [
    {
      "name": "Игорь"
    },
    {
      "name": "Катя",
      "color": "#e5ee68"
    },
    {
      "name": "Кирилл",
      "color": "#08f758"
    },
    {
      "name": "Миша",
      "color": "#d78304"
    }
  ]
}